speculator
