Metadata-Version: 1.1
Name: speculator
Version: 1.0.2
Summary: Speculator predicts the price trend of cryptocurrencies like Bitcoin and Ethereum with machine learning models and technical analysis.
Home-page: https://github.com/amicks/Speculator
Author: Allston Mickey
Author-email: allston.mickey@gmail.com
License: MIT
Download-URL: https://github.com/amicks/Speculator/archive/1.0.0.tar.gz
Keywords: finance,price,trend,analysis,machine learning,artificial intelligence,bitcoin,ethereum,cryptocurrency,crypto,api,REST,web
Platform: UNKNOWN
Classifier: Development Status :: 4 - Beta
Classifier: Framework :: Flask
Classifier: Intended Audience :: Education
Classifier: Intended Audience :: Developers
Classifier: Intended Audience :: Financial and Insurance Industry
Classifier: License :: OSI Approved :: MIT License
Classifier: Natural Language :: English
Classifier: Programming Language :: Python :: 3.6
Classifier: Topic :: Office/Business :: Financial :: Investment
Classifier: Topic :: Scientific/Engineering :: Artificial Intelligence
Classifier: Topic :: Software Development :: Libraries :: Python Modules
